globalreportcreater/__init__.py
globalreportcreater/__main__.py
globalreportcreater/proc.py
globalreportcreater-0.1.0.dist-info/METADATA
globalreportcreater-0.1.0.dist-info/WHEEL
globalreportcreater-0.1.0.dist-info/entry_points.txt
globalreportcreater-0.1.0.dist-info/top_level.txt
globalreportcreater-0.1.0.dist-info/RECORD
