Metadata-Version: 2.1
Name: globalreportcreater
Version: 0.1.0
Summary: A package for create global report
Author-email: Dusya <Lev.khrobostov@mail.ru>
License: MIT
